rdkit-stubs/RDConfig.pyi
rdkit-stubs/RDLogger.pyi
rdkit-stubs/RDPaths.pyi
rdkit-stubs/RDRandom.pyi
rdkit-stubs/TestRunner.pyi
rdkit-stubs/__init__.pyi
rdkit-stubs/rdBase.pyi
rdkit-stubs/Avalon/__init__.pyi
rdkit-stubs/Avalon/pyAvalonTools.pyi
rdkit-stubs/Chem/AllChem.pyi
rdkit-stubs/Chem/BRICS.pyi
rdkit-stubs/Chem/BuildFragmentCatalog.pyi
rdkit-stubs/Chem/ChemicalFeatures.pyi
rdkit-stubs/Chem/ChemicalForceFields.pyi
rdkit-stubs/Chem/Crippen.pyi
rdkit-stubs/Chem/DSViewer.pyi
rdkit-stubs/Chem/Descriptors.pyi
rdkit-stubs/Chem/Descriptors3D.pyi
rdkit-stubs/Chem/EnumerateHeterocycles.pyi
rdkit-stubs/Chem/EnumerateStereoisomers.pyi
rdkit-stubs/Chem/FastSDMolSupplier.pyi
rdkit-stubs/Chem/FeatFinderCLI.pyi
rdkit-stubs/Chem/FilterCatalog.pyi
rdkit-stubs/Chem/FragmentCatalog.pyi
rdkit-stubs/Chem/FragmentMatcher.pyi
rdkit-stubs/Chem/Fragments.pyi
rdkit-stubs/Chem/FunctionalGroups.pyi
rdkit-stubs/Chem/GraphDescriptors.pyi
rdkit-stubs/Chem/Graphs.pyi
rdkit-stubs/Chem/Lipinski.pyi
rdkit-stubs/Chem/MACCSkeys.pyi
rdkit-stubs/Chem/MCS.pyi
rdkit-stubs/Chem/MolCatalog.pyi
rdkit-stubs/Chem/MolSurf.pyi
rdkit-stubs/Chem/PandasTools.pyi
rdkit-stubs/Chem/PropertyMol.pyi
rdkit-stubs/Chem/PyMol.pyi
rdkit-stubs/Chem/QED.pyi
rdkit-stubs/Chem/Randomize.pyi
rdkit-stubs/Chem/Recap.pyi
rdkit-stubs/Chem/ReducedGraphs.pyi
rdkit-stubs/Chem/SATIS.pyi
rdkit-stubs/Chem/SaltRemover.pyi
rdkit-stubs/Chem/ShowMols.pyi
rdkit-stubs/Chem/TemplateAlign.pyi
rdkit-stubs/Chem/TorsionFingerprints.pyi
rdkit-stubs/Chem/__init__.pyi
rdkit-stubs/Chem/inchi.pyi
rdkit-stubs/Chem/rdAbbreviations.pyi
rdkit-stubs/Chem/rdCIPLabeler.pyi
rdkit-stubs/Chem/rdChemReactions.pyi
rdkit-stubs/Chem/rdChemicalFeatures.pyi
rdkit-stubs/Chem/rdCoordGen.pyi
rdkit-stubs/Chem/rdDepictor.pyi
rdkit-stubs/Chem/rdDeprotect.pyi
rdkit-stubs/Chem/rdDistGeom.pyi
rdkit-stubs/Chem/rdEHTTools.pyi
rdkit-stubs/Chem/rdFMCS.pyi
rdkit-stubs/Chem/rdFingerprintGenerator.pyi
rdkit-stubs/Chem/rdForceFieldHelpers.pyi
rdkit-stubs/Chem/rdFreeSASA.pyi
rdkit_stubs-0.8.dist-info/LICENSE-APACHE
rdkit_stubs-0.8.dist-info/LICENSE-MIT
rdkit_stubs-0.8.dist-info/METADATA
rdkit_stubs-0.8.dist-info/WHEEL
rdkit_stubs-0.8.dist-info/top_level.txt
rdkit_stubs-0.8.dist-info/RECORD
