Metadata-Version: 2.1
Name: rdkit-stubs
Version: 0.8
Summary: type stubs for rdkit
Author: K. Yanagisawa
Author-email: Andrew Dirksen <andrew@dirksen.com>, Ryan Rightmer <rrightmer@gmail.com>
License: MIT OR Apache-2.0
Project-URL: Homepage, https://github.com/postera-ai/rdkit-stubs
Keywords: stubs,rdkit,typing
Classifier: Development Status :: 1 - Planning
Classifier: Typing :: Stubs Only
Classifier: Programming Language :: Python :: 3.10
Requires-Python: >=3.10
License-File: LICENSE-APACHE
License-File: LICENSE-MIT
